[
  {
    "runId": 14712004107,
    "runUniqueId": "14712004107_1745855294576",
    "testResult": "PASS",
    "timestamp": 1745855254045,
    "summary": {
      "statistic": {
        "failed": 0,
        "broken": 0,
        "skipped": 0,
        "passed": 2,
        "unknown": 0,
        "total": 2
      },
      "time": {
        "start": 1745855254045,
        "stop": 1745855286301,
        "duration": 32256,
        "minDuration": 29577,
        "maxDuration": 30469,
        "sumDuration": 60046
      }
    }
  }
]